pydwarfs/VERSION
pydwarfs/__init__.py
pydwarfs/dwarfs.py
pydwarfs/dwarfsextract.py
pydwarfs/exceptions.py
pydwarfs/utils.py
pydwarfs-0.3.1.dist-info/LICENSE
pydwarfs-0.3.1.dist-info/METADATA
pydwarfs-0.3.1.dist-info/WHEEL
pydwarfs-0.3.1.dist-info/top_level.txt
pydwarfs-0.3.1.dist-info/RECORD
