Metadata-Version: 2.1
Name: pydwarfs
Version: 0.3.1
Summary: A wrapper of DwarFS command line utility
Author: nukemiko
License: MIT License
Project-URL: Repository, https://github.com/nukemiko/pydwarfs
Project-URL: Issues, https://github.com/nukemiko/pydwarfs/issues
Project-URL: Changelog, https://github.com/nukemiko/pydwarfs/blob/master/CHANGELOG.md
Keywords: dwarfs
Classifier: Programming Language :: Python :: 3
Classifier: License :: OSI Approved :: MIT License
Classifier: Operating System :: POSIX :: Linux
Requires-Python: >=3.10
License-File: LICENSE
Requires-Dist: attrs
Requires-Dist: mntfinder >=0.1.1
